{"plyCateByCodeMap":{},"playCateMap":{},"SXS_N":[["11","23","35","47"],["10","22","34","46"],["09","21","33","45"],["08","20","32","44"],["07","19","31","43"],["06","18","30","42"],["05","17","29","41"],["04","16","28","40"],["03","15","27","39"],["02","14","26","38"],["01","13","25","37","49"],["12","24","36","48"]],"playByIdMap":{},"WEI":[["10","20","30","40"],["01","11","21","31","41"],["02","12","22","32","42"],["03","13","23","33","43"],["04","14","24","34","44"],["05","15","25","35","45"],["06","16","26","36","46"],["07","17","27","37","47"],["08","18","28","38","48"],["09","19","29","39","49"]],"playMap":{},"SXS":["鼠","牛","虎","兔","龙","蛇","马","羊","猴","鸡","狗","猪"]}